LICENSE
MANIFEST.in
README.rst
optirx.py
setup.py
optirx.egg-info/PKG-INFO
optirx.egg-info/SOURCES.txt
optirx.egg-info/dependency_links.txt
optirx.egg-info/top_level.txt
test/test_unpack.py