Metadata-Version: 1.1
Name: optirx
Version: 0.3
Summary: A pure Python library to receive motion capture data from OptiTrack Streaming Engine
Home-page: https://bitbucket.org/astanin/python-optirx
Author: Sergey Astanin
Author-email: s.astanin@gmail.com
License: The MIT License (MIT)
